{
	"partitions" : [
		{
			"name" : "Top",
			"pins" : [
				{
					"name" : "Ax_t[0]",
					"strict" : false
				},
				{
					"name" : "Ax_t[1]",
					"strict" : false
				},
				{
					"name" : "Ax_t[2]",
					"strict" : false
				},
				{
					"name" : "Ax_t[3]",
					"strict" : false
				},
				{
					"name" : "Ax_t[4]",
					"strict" : false
				},
				{
					"name" : "Ax_t[5]",
					"strict" : false
				},
				{
					"name" : "Ax_t[6]",
					"strict" : false
				},
				{
					"name" : "Ax_t[7]",
					"strict" : false
				},
				{
					"name" : "Bx_t[0]",
					"strict" : false
				},
				{
					"name" : "Bx_t[1]",
					"strict" : false
				},
				{
					"name" : "Bx_t[2]",
					"strict" : false
				},
				{
					"name" : "Bx_t[3]",
					"strict" : false
				},
				{
					"name" : "Bx_t[4]",
					"strict" : false
				},
				{
					"name" : "Bx_t[5]",
					"strict" : false
				},
				{
					"name" : "Bx_t[6]",
					"strict" : false
				},
				{
					"name" : "Bx_t[7]",
					"strict" : false
				},
				{
					"name" : "Cx_t[0]",
					"strict" : false
				},
				{
					"name" : "Cx_t[1]",
					"strict" : false
				},
				{
					"name" : "Cx_t[2]",
					"strict" : false
				},
				{
					"name" : "Cx_t[3]",
					"strict" : false
				},
				{
					"name" : "Cx_t[4]",
					"strict" : false
				},
				{
					"name" : "Cx_t[5]",
					"strict" : false
				},
				{
					"name" : "Cx_t[6]",
					"strict" : false
				},
				{
					"name" : "Cx_t[7]",
					"strict" : false
				},
				{
					"name" : "x_t[0]",
					"strict" : false
				},
				{
					"name" : "x_t[1]",
					"strict" : false
				},
				{
					"name" : "x_t[2]",
					"strict" : false
				},
				{
					"name" : "x_t[3]",
					"strict" : false
				},
				{
					"name" : "x_t[4]",
					"strict" : false
				},
				{
					"name" : "x_t[5]",
					"strict" : false
				},
				{
					"name" : "x_t[6]",
					"strict" : false
				},
				{
					"name" : "x_t[7]",
					"strict" : false
				},
				{
					"name" : "y_t[0]",
					"strict" : false
				},
				{
					"name" : "y_t[1]",
					"strict" : false
				},
				{
					"name" : "y_t[2]",
					"strict" : false
				},
				{
					"name" : "y_t[3]",
					"strict" : false
				},
				{
					"name" : "y_t[4]",
					"strict" : false
				},
				{
					"name" : "y_t[5]",
					"strict" : false
				},
				{
					"name" : "y_t[6]",
					"strict" : false
				},
				{
					"name" : "y_t[7]",
					"strict" : false
				},
				{
					"name" : "r_t[0]",
					"strict" : false
				},
				{
					"name" : "r_t[1]",
					"strict" : false
				},
				{
					"name" : "r_t[2]",
					"strict" : false
				},
				{
					"name" : "r_t[3]",
					"strict" : false
				},
				{
					"name" : "r_t[4]",
					"strict" : false
				},
				{
					"name" : "r_t[5]",
					"strict" : false
				},
				{
					"name" : "r_t[6]",
					"strict" : false
				},
				{
					"name" : "r_t[7]",
					"strict" : false
				},
				{
					"name" : "ALU_t[0]",
					"strict" : false
				},
				{
					"name" : "ALU_t[1]",
					"strict" : false
				},
				{
					"name" : "ALU_t[2]",
					"strict" : false
				},
				{
					"name" : "ALU_t[3]",
					"strict" : false
				},
				{
					"name" : "ALU_t[4]",
					"strict" : false
				},
				{
					"name" : "ALU_t[5]",
					"strict" : false
				},
				{
					"name" : "ALU_t[6]",
					"strict" : false
				},
				{
					"name" : "ALU_t[7]",
					"strict" : false
				},
				{
					"name" : "Bus_t[0]",
					"strict" : false
				},
				{
					"name" : "Bus_t[1]",
					"strict" : false
				},
				{
					"name" : "Bus_t[2]",
					"strict" : false
				},
				{
					"name" : "Bus_t[3]",
					"strict" : false
				},
				{
					"name" : "Bus_t[4]",
					"strict" : false
				},
				{
					"name" : "Bus_t[5]",
					"strict" : false
				},
				{
					"name" : "Bus_t[6]",
					"strict" : false
				},
				{
					"name" : "Bus_t[7]",
					"strict" : false
				},
				{
					"name" : "DATA_BUS_OUT[0]",
					"strict" : false
				},
				{
					"name" : "DATA_BUS_OUT[1]",
					"strict" : false
				},
				{
					"name" : "DATA_BUS_OUT[2]",
					"strict" : false
				},
				{
					"name" : "DATA_BUS_OUT[3]",
					"strict" : false
				},
				{
					"name" : "DATA_BUS_OUT[4]",
					"strict" : false
				},
				{
					"name" : "DATA_BUS_OUT[5]",
					"strict" : false
				},
				{
					"name" : "DATA_BUS_OUT[6]",
					"strict" : false
				},
				{
					"name" : "DATA_BUS_OUT[7]",
					"strict" : false
				},
				{
					"name" : "ADDR_BUS[0]",
					"strict" : false
				},
				{
					"name" : "ADDR_BUS[1]",
					"strict" : false
				},
				{
					"name" : "ADDR_BUS[2]",
					"strict" : false
				},
				{
					"name" : "ADDR_BUS[3]",
					"strict" : false
				},
				{
					"name" : "ADDR_BUS[4]",
					"strict" : false
				},
				{
					"name" : "ADDR_BUS[5]",
					"strict" : false
				},
				{
					"name" : "ADDR_BUS[6]",
					"strict" : false
				},
				{
					"name" : "ADDR_BUS[7]",
					"strict" : false
				},
				{
					"name" : "SRC_UC[3]",
					"strict" : false
				},
				{
					"name" : "SelSRC",
					"strict" : false
				},
				{
					"name" : "SRC_UC[0]",
					"strict" : false
				},
				{
					"name" : "SRC_UC[1]",
					"strict" : false
				},
				{
					"name" : "SRC_UC[2]",
					"strict" : false
				},
				{
					"name" : "SRC_UC[4]",
					"strict" : false
				},
				{
					"name" : "Fx[0]",
					"strict" : false
				},
				{
					"name" : "Fx[1]",
					"strict" : false
				},
				{
					"name" : "Fx[2]",
					"strict" : false
				},
				{
					"name" : "Fx[3]",
					"strict" : false
				},
				{
					"name" : "Fx[4]",
					"strict" : false
				},
				{
					"name" : "Fx[5]",
					"strict" : false
				},
				{
					"name" : "Fx[6]",
					"strict" : false
				},
				{
					"name" : "Fx[7]",
					"strict" : false
				},
				{
					"name" : "DST_UC[2]",
					"strict" : false
				},
				{
					"name" : "SelDST",
					"strict" : false
				},
				{
					"name" : "DST_UC[0]",
					"strict" : false
				},
				{
					"name" : "DST_UC[3]",
					"strict" : false
				},
				{
					"name" : "DST_UC[4]",
					"strict" : false
				},
				{
					"name" : "DST_UC[1]",
					"strict" : false
				},
				{
					"name" : "Cmd[2]",
					"strict" : false
				},
				{
					"name" : "Cmd[0]",
					"strict" : false
				},
				{
					"name" : "Cmd[1]",
					"strict" : false
				},
				{
					"name" : "Reloj",
					"strict" : false
				},
				{
					"name" : "Reset",
					"strict" : false
				},
				{
					"name" : "Enable_r",
					"strict" : false
				},
				{
					"name" : "DATA_BUS_IN[0]",
					"strict" : false
				},
				{
					"name" : "SelMDR",
					"strict" : false
				},
				{
					"name" : "SelMAR",
					"strict" : false
				},
				{
					"name" : "DATA_BUS_IN[1]",
					"strict" : false
				},
				{
					"name" : "DATA_BUS_IN[2]",
					"strict" : false
				},
				{
					"name" : "DATA_BUS_IN[3]",
					"strict" : false
				},
				{
					"name" : "DATA_BUS_IN[4]",
					"strict" : false
				},
				{
					"name" : "DATA_BUS_IN[5]",
					"strict" : false
				},
				{
					"name" : "DATA_BUS_IN[6]",
					"strict" : false
				},
				{
					"name" : "DATA_BUS_IN[7]",
					"strict" : false
				}
			]
		}
	]
}